VIIRS_tiled_granules/VIIRS_tiled_granule.py
VIIRS_tiled_granules/VIIRS_tiled_granules.py
VIIRS_tiled_granules/__init__.py
VIIRS_tiled_granules/authenticate.py
VIIRS_tiled_granules/concept_ID_from_DOI.py
VIIRS_tiled_granules/connection.py
VIIRS_tiled_granules/constants.py
VIIRS_tiled_granules/exceptions.py
VIIRS_tiled_granules/granule_ID.py
VIIRS_tiled_granules/retrieve_granule.py
VIIRS_tiled_granules/search_granules.py
VIIRS_tiled_granules/version.py
viirs_tiled_granules-1.1.1.dist-info/licenses/LICENSE
viirs_tiled_granules-1.1.1.dist-info/METADATA
viirs_tiled_granules-1.1.1.dist-info/WHEEL
viirs_tiled_granules-1.1.1.dist-info/top_level.txt
viirs_tiled_granules-1.1.1.dist-info/RECORD
