Metadata-Version: 2.4
Name: VIIRS-tiled-granules
Version: 1.1.1
Summary: Visible Infrared Imaging Radiometer Suite (VIIRS) Sinusoidal Tile Product Search and Download Utility
Author-email: "Gregory H. Halverson" <gregory.h.halverson@jpl.nasa.gov>, Evan Davis <evan.w.davis@jpl.nasa.gov>
Project-URL: Homepage, https://github.com/JPL-Evapotranspiration-Algorithms/VIIRS-Tiled-Granules
Classifier: Programming Language :: Python :: 3
Classifier: Operating System :: OS Independent
Requires-Python: >=3.10
License-File: LICENSE
Requires-Dist: colored-logging
Requires-Dist: earthaccess
Requires-Dist: modland>=1.1.0
Requires-Dist: python-dateutil
Requires-Dist: rasters
Requires-Dist: requests
Provides-Extra: dev
Requires-Dist: build; extra == "dev"
Requires-Dist: pytest>=6.0; extra == "dev"
Requires-Dist: pytest-cov; extra == "dev"
Requires-Dist: jupyter; extra == "dev"
Requires-Dist: pytest; extra == "dev"
Requires-Dist: twine; extra == "dev"
Dynamic: license-file
